Workbook
Name aporte: Investimento!$C$15:$C$15
Name patrimonio: Investimento!$C$18:$C$18
Name qnt_anos: Investimento!$C$16:$C$16
Name rendimento_carteira: Investimento!$C$11:$C$11
Name salario: Investimento!$C$10:$C$10
Name sugestao_investimento: Investimento!$C$12:$C$12
Name taxa_mensal: Investimento!$C$17:$C$17

Sheet Investimento
B9: Configurações
B10: Salário | C10: 5000
B11: Rendimento Carteira | C11: 0.009
B12: Sugestão Investimento | C12: =C10*30% -> 1500
B14: INVESTIMENTO MENSAL
B15: Quanto investir por mês? | C15: 500
B16: Por quantos anos? | C16: 5
B17: Taxa de rendimento mensal? | C17: 0.01079
B18: Quanto de patrimônio acumulado? | C18: {=FV(taxa_mensal,qnt_anos*12,aporte*-1)} -> 41888.457
B19: Dividendos mensais? | C19: {=patrimonio*rendimento_carteira} -> 376.99611
B21: CENÁRIOS | D21: Dividendo
A22: 2 | B22: Rendimento em 2 anos? | C22: =FV($C$17,$A22*12,$C$15*-1) -> 13613.814 | D22: {=C22*rendimento_carteira} -> 122.52432
A23: 5 | B23: Rendimento em 5 anos? | C23: =FV($C$17,$A23*12,$C$15*-1) -> 41888.457 | D23: {=C23*rendimento_carteira} -> 376.99611
A24: 10 | B24: Rendimento em 10 anos? | C24: =FV($C$17,$A24*12,$C$15*-1) -> 121642.11 | D24: {=C24*rendimento_carteira} -> 1094.779
A25: 20 | B25: Rendimento em 20 anos? | C25: =FV($C$17,$A25*12,$C$15*-1) -> 562599.2 | D25: {=C25*rendimento_carteira} -> 5063.3928
A26: 30 | B26: Rendimento em 30 anos? | C26: =FV($C$17,$A26*12,$C$15*-1) -> 2161084.8 | D26: {=C26*rendimento_carteira} -> 19449.763
B29: PERFIL | C29: Agressivo
B30: VALOR INVESTIDO POR MÊS | C30: {=aporte} -> 500
B31: TIPO DE FII | C31: Percentual Sugerido | D31: Valores
B32: PAPEL | C32: =VLOOKUP($C$29&"_"&B32,Normalize!A:D,4,FALSE) -> 0.5 | D32: =C32*$C$30 -> 250
B33: TIJOLO | C33: =VLOOKUP($C$29&"_"&B33,Normalize!A:D,4,FALSE) -> 0.1 | D33: =C33*$C$30 -> 50
B34: HÍBRIDO | C34: =VLOOKUP($C$29&"_"&B34,Normalize!A:D,4,FALSE) -> 0.05 | D34: =C34*$C$30 -> 25
B35: FOFs | C35: =VLOOKUP($C$29&"_"&B35,Normalize!A:D,4,FALSE) -> 0.05 | D35: =C35*$C$30 -> 25
B36: DESENVOLVIMENTO | C36: =VLOOKUP($C$29&"_"&B36,Normalize!A:D,4,FALSE) -> 0.2 | D36: =C36*$C$30 -> 100
B37: HOTELARIAS | C37: =VLOOKUP($C$29&"_"&B37,Normalize!A:D,4,FALSE) -> 0.1 | D37: =C37*$C$30 -> 50
D38: =SUM(D32:D37) -> 500

Sheet Normalize
A2: CHAVE | B2: PERFIL | C2: TIPO DE FII | D2: %
A3: =B3&"_"&C3 -> Conservador_PAPEL | B3: Conservador | C3: PAPEL | D3: 0.3
A4: =B4&"_"&C4 -> Conservador_TIJOLO | B4: Conservador | C4: TIJOLO | D4: 0.5
A5: =B5&"_"&C5 -> Conservador_HÍBRIDO | B5: Conservador | C5: HÍBRIDO | D5: 0.1
A6: =B6&"_"&C6 -> Conservador_FOFs | B6: Conservador | C6: FOFs | D6: 0.1
A7: =B7&"_"&C7 -> Conservador_DESENVOLVIMENTO | B7: Conservador | C7: DESENVOLVIMENTO | D7: 0
A8: =B8&"_"&C8 -> Conservador_HOTELARIAS | B8: Conservador | C8: HOTELARIAS | D8: 0
A9: =B9&"_"&C9 -> Moderado_PAPEL | B9: Moderado | C9: PAPEL | D9: 0.32
A10: =B10&"_"&C10 -> Moderado_TIJOLO | B10: Moderado | C10: TIJOLO | D10: 0.35
A11: =B11&"_"&C11 -> Moderado_HÍBRIDO | B11: Moderado | C11: HÍBRIDO | D11: 0.08
A12: =B12&"_"&C12 -> Moderado_FOFs | B12: Moderado | C12: FOFs | D12: 0.05
A13: =B13&"_"&C13 -> Moderado_DESENVOLVIMENTO | B13: Moderado | C13: DESENVOLVIMENTO | D13: 0.1
A14: =B14&"_"&C14 -> Moderado_HOTELARIAS | B14: Moderado | C14: HOTELARIAS | D14: 0.1
... A20: =B20&"_"&C20 -> Agressivo_HOTELARIAS | B20: Agressivo | C20: HOTELARIAS | D20: 0.1
